tabaml/__init__.py
tabaml/binary_cls.py
tabaml/example.py
tabaml/generate.py
tabaml/metrics.py
tabaml/multi_cls.py
tabaml/utils.py
tabaml-0.2.2.dist-info/METADATA
tabaml-0.2.2.dist-info/WHEEL
tabaml-0.2.2.dist-info/top_level.txt
tabaml-0.2.2.dist-info/RECORD
