Metadata-Version: 2.4
Name: tabaml
Version: 0.2.2
Summary: TabAML is a framework for tabular data classification models
Author-email: xiaoql <xiaoql@hollycrm.com>
Project-URL: Homepage, https://github.com/Qiliang/tabaml
Project-URL: Issues, https://github.com/Qiliang/tabaml/issues
Classifier: Programming Language :: Python :: 3
Classifier: License :: OSI Approved :: MIT License
Classifier: Operating System :: OS Independent
Requires-Python: >=3.9
Requires-Dist: fastparquet>=2024.11.0
Requires-Dist: numpy
Requires-Dist: pandas
Requires-Dist: torch
